pympipool/__init__.py
pympipool-0.9.1.dist-info/METADATA
pympipool-0.9.1.dist-info/WHEEL
pympipool-0.9.1.dist-info/top_level.txt
pympipool-0.9.1.dist-info/RECORD
