Metadata-Version: 2.1
Name: pympipool
Version: 0.9.1
Summary: Scale serial and MPI-parallel python functions over hundreds of compute nodes all from within a jupyter notebook or serial python process.
Author-email: Jan Janssen <janssen@lanl.gov>
Project-URL: Homepage, https://github.com/pyiron/executorlib
Project-URL: Documentation, https://executorlib.readthedocs.io
Project-URL: Repository, https://github.com/pyiron/executorlib
Keywords: pyiron
Classifier: Development Status :: 5 - Production/Stable
Classifier: Topic :: Scientific/Engineering :: Physics
Classifier: License :: OSI Approved :: BSD License
Classifier: Intended Audience :: Science/Research
Classifier: Operating System :: OS Independent
Classifier: Programming Language :: Python :: 3.9
Classifier: Programming Language :: Python :: 3.10
Classifier: Programming Language :: Python :: 3.11
Classifier: Programming Language :: Python :: 3.12
Requires-Python: <3.13,>=3.9
Requires-Dist: executorlib
